Workbook

Sheet ETF Due Diligence
A1: ETF DUE DILIGENCE — VWRA · ITPS · AGGU
A2: Relatório atualizado com dados oficiais dos emissores e framework etf-main-metrics.md | Agosto de 2026
A4: STORY IN BRIEF
A5: Os três fundos são UCITS irlandeses, de acumulação e emitidos por gestores de primeira linha. VWRA entrega o motor de crescimento global, mas mantém concentração material nos EUA e nas maiores empresas; ITPS adiciona proteção contra inflação americana, com risco relevante de duração e juros reais; AGGU amplia a diversificação em renda fixa investment grade e reduz a volatilidade cambial por meio do hedge para USD. A taxa ponderada da alocação-modelo é baixa, mas spread e prêmio/desconto sobre NAV devem ser verificados no momento da ordem. O ticker ITPS na LSE negocia em GBP; para negociação em USD na LSE, a linha oficial é IDTP.
A10: INDICADORES DA ALOCAÇÃO-MODELO
A11: TER ponderado | B11: =SUMPRODUCT(C39:C41,D39:D41) -> 0.00124 | C11: Duração RF ponderada | D11: =SUMPRODUCT(C40:C41,'ETF Sources'!V3:V4)/SUM(C40:C41) -> 6.37375 | E11: Menor AUM de classe | F11: =MIN(F39:F41) -> 3534875907 | G11: 3/3 UCITS Irlanda
A12: Custo anual sobre USD 200 mil | B12: =B11*200000 -> 248
A13: MATRIZ DE DUE DILIGENCE POR PRIORIDADE
A14: Tier | B14: Métrica | C14: VWRA | D14: ITPS | E14: AGGU | F14: Leitura pragmática | G14: Data-base
A15: Tier 1 | B15: Domicílio / UCITS | C15: Irlanda / Sim | D15: Irlanda / Sim | E15: Irlanda / Sim | F15: Estrutura alinhada ao escopo UCITS; tratamento fiscal individual exige validação profissional. | G15: Ago/2026
A16: Tier 1 | B16: ISIN | C16: IE00BK5BQT80 | D16: IE00B1FZSC47 | E16: IE00BZ043R46 | F16: Identificadores confirmados nas páginas oficiais. | G16: Ago/2026
A17: Tier 1 | B17: Benchmark / escopo | C17: FTSE All-World | D17: BBG US Govt Inflation-Linked | E17: BBG Global Aggregate | F17: Ações globais large/mid; TIPS dos EUA; bonds globais investment grade. | G17: Ago/2026
A18: Tier 1 | B18: Início da classe | C18: 43669 | D18: 08/dez/2006 | E18: 43060 | F18: Todos possuem histórico operacional relevante; VWRA é a classe mais recente. | G18: Ago/2026
A19: Tier 1 | B19: Réplica / renda | C19: Física amostrada / acum. | D19: Física amostrada / acum. | E19: Física amostrada / acum. | F19: Os três acumulam rendimentos no patrimônio da classe. | G19: Ago/2026
A20: Tier 2 | B20: TER / OCF | C20: ='ETF Sources'!N2 -> 0.0014 | D20: ='ETF Sources'!N3 -> 0.001 | E20: ='ETF Sources'!N4 -> 0.001 | F20: Custos declarados baixos; comparar também tracking e execução. | G20: Ago/2026
A21: Tier 2 | B21: AUM da classe | C21: ='ETF Sources'!O2 -> 53360000000 | D21: ='ETF Sources'!O3 -> 3534875907 | E21: ='ETF Sources'!O4 -> 4110903665 | F21: Escala robusta nos três fundos; risco de fechamento parece baixo. | G21: Ago/2026
A22: Tier 2 | B22: Tracking | C22: ='ETF Sources'!Y2 -> 0.0007 | D22: N/D | E22: N/D | F22: VWRA: tracking error de 1 ano; tracking difference não foi divulgado nos trechos consultados. | G22: 46174
A23: Tier 2 | B23: Execução | C23: Checar ao vivo | D23: Checar ao vivo | E23: Checar ao vivo | F23: Spread e prêmio/desconto sobre NAV são intradiários; validar na IBKR antes da ordem. | G23: Na ordem
A24: Tier 3 | B24: Número de posições | C24: ='ETF Sources'!Q2 -> 3782 | D24: ='ETF Sources'!Q3 -> 48 | E24: ='ETF Sources'!Q4 -> 19980 | F24: VWRA diversifica ações; ITPS é concentrado em Treasuries; AGGU é muito granular. | G24: Ago/2026
A25: Tier 3 | B25: Concentração-chave | C25: ='ETF Sources'!AC2 -> 0.2269921 | D25: 99,93% US Treasury | E25: 53,10% Treasuries | F25: Concentração deve ser interpretada por classe: empresas no equity e emissores nos bonds. | G25: Ago/2026
A26: Tier 3 | B26: EUA / valuation | C26: 61,7% EUA | P/E 23,2x | D26: N/A — soberano EUA | E26: N/A — renda fixa global | F26: VWRA mantém peso elevado nos EUA e valuation agregado relevante. | G26: 46174
A27: Tier 4 | B27: NAV | C27: ='ETF Sources'!R2 -> 190.57 | D27: ='ETF Sources'!R3 -> 256.12 | E27: ='ETF Sources'!R4 -> 5.83 | F27: NAV não substitui preço de execução em bolsa. | G27: Ago/2026
A28: Tier 4 | B28: YTM / real yield | C28: N/A | D28: ='ETF Sources'!T3 -> 0.0454 | E28: ='ETF Sources'!T4 -> 0.0397 | F28: ITPS oferece yield real explícito; AGGU oferece yield nominal diversificado. | G28: Ago/2026
A29: Tier 4 | B29: Duração / maturidade | C29: N/A | D29: 6,55 / 7,39 anos | E29: 6,08 / 8,05 anos | F29: Ambos os fundos de bonds têm duração próxima de seis anos. | G29: Ago/2026
A30: Tier 5 | B30: Retorno YTD | C30: N/D | D30: ='ETF Sources'!S3 -> 0.0039 | E30: ='ETF Sources'!S4 -> 0.0051 | F30: Somente sanity check; não usar retorno recente como critério principal. | G30: Ago/2026
A31: Tier 5 | B31: Volatilidade 3 anos | C31: N/D | D31: ='ETF Sources'!X3 -> 0.0439 | E31: ='ETF Sources'!X4 -> 0.0412 | F31: Útil para dimensionar risco de renda fixa, não para prever retornos. | G31: 46204
A32: Conclusão | B32: Papel no portfólio | C32: Crescimento global | D32: Inflação EUA | E32: Estabilizador global | F32: Combinação coerente 60/25/15; maior risco estrutural permanece no bloco acionário. | G32: Atual
A37: IMPACTO NA ALOCAÇÃO 60 / 25 / 15
A38: Ticker | B38: Papel | C38: Peso | D38: TER | E38: Contribuição à TER | F38: AUM da classe | G38: Observação
A39: VWRA | B39: Crescimento global | C39: 0.6 | D39: ='ETF Sources'!N2 -> 0.0014 | E39: =C39*D39 -> 0.00084 | F39: ='ETF Sources'!O2 -> 53360000000 | G39: Concentração EUA 61,7%; top 10 = 22,7%.
A40: ITPS | B40: Proteção inflação EUA | C40: 0.25 | D40: ='ETF Sources'!N3 -> 0.001 | E40: =C40*D40 -> 0.00025 | F40: ='ETF Sources'!O3 -> 3534875907 | G40: Ticker ITPS na LSE é negociado em GBP; USD = IDTP.
A41: AGGU | B41: Renda fixa global hedged USD | C41: 0.15 | D41: ='ETF Sources'!N4 -> 0.001 | E41: =C41*D41 -> 0.00015 | F41: ='ETF Sources'!O4 -> 4110903665 | G41: Diversificação investment grade; duração 6,08 anos.
A42: Total / média ponderada | C42: 1 | E42: =SUM(E39:E41) -> 0.00124
A44: LIMITAÇÕES E PRÓXIMA AÇÃO
A45: Antes de executar, conferir spread bid-ask, prêmio/desconto sobre NAV e moeda da linha negociada. Tracking difference de 3–5 anos não estava disponível de forma explícita nas páginas consultadas; o relatório usa tracking error quando divulgado e marca os demais campos como N/D. Este material descreve mecanismos estruturais e não estabelece alíquotas, limites ou obrigações fiscais; confirme o tratamento aplicável com contador ou assessor tributário.
A49: Fontes detalhadas, URLs e datas: consulte a aba ETF Sources.
A52: REVISÃO CRÍTICA DO RELATÓRIO ALTERNATIVO
A53: Conclusão: a análise alternativa é forte na tese econômica e no desenho 60/25/15, mas é excessivamente categórica em tributação e sucessão. O núcleo quantitativo confirmado é TER ponderado de 12,4 bps, custo anual estimado de USD 248, UCITS irlandês, acumulação e papéis complementares dos três ETFs. Antes de uso decisório, devem ser corrigidos o ticker de ITPS para ordens em USD, as afirmações sobre tributação de classes Acc, IOF, compensação de perdas, tracking difference e proteção contra IPCA.
A57: Tema | B57: Veredito | C57: Análise alternativa | D57: Evidência / correção | E57: Impacto | F57: Confiança | G57: Ação recomendada
A58: Alocação 60/25/15 | B58: Confirmado | C58: Estrutura simples de três pilares. | D58: Coerente com o modelo da pasta: crescimento global, TIPS e bonds globais hedged. | E58: Mantém simplicidade e diversificação funcional. | F58: Alta | G58: Manter como alocação-alvo, sujeita ao perfil de risco.
A59: TER ponderado | B59: Confirmado | C59: 12,4 bps; USD 248/ano sobre USD 200 mil. | D59: 0,60×0,14% + 0,25×0,10% + 0,15×0,10% = 0,124%. | E59: Custo explícito baixo. | F59: Alta | G59: Usar como custo declarado, não como custo total.
A60: US Estate Tax | B60: Parcial | C60: Estrutura irlandesa seria blindagem integral e única. | D60: Ações de corporações americanas são US-situs; o IRS exige Form 706-NA acima de USD 60 mil. ETFs irlandeses reduzem essa exposição direta, mas “única” e “integral” são termos absolutos que exigem parecer sucessório. | E60: Relevante para não residentes/não cidadãos dos EUA. | F60: Média-alta | G60: Substituir por “mitiga exposição direta a ativos US-situs”; validar residência, domicílio e titularidade.
A61: WHT Irlanda–EUA | B61: Parcial | C61: Redução de 30% para 15% e ausência de bitributação individual. | D61: O tratado pode reduzir retenção sobre dividendos recebidos pelo fundo irlandês; isso é leakage no nível do fundo. Não equivale automaticamente a eliminar toda tributação do investidor brasileiro. | E61: Afeta retorno líquido de VWRA. | F61: Média | G61: Descrever mecanismo no nível do fundo e evitar promessa de economia individual fixa.
A62: Classes Acc / Lei 14.754 | B62: Não comprovado | C62: IR somente na alienação e diferimento total. | D62: O wrapper Acc elimina distribuição de caixa, mas o tratamento brasileiro depende da classificação jurídica e das regras vigentes. A própria fonte fornecida exige consulta profissional. | E62: Pode alterar timing do imposto. | F62: Média-baixa | G62: Remover “garante diferimento total”; obter parecer tributário escrito.
A63: Isenção R$35 mil | B63: Provável, mas validar | C63: Extinta para vendas no exterior. | D63: A Lei 14.754/2023 instituiu regime anual de aplicações financeiras no exterior; aplicar a regra ao caso e ao ano-calendário exige validação atualizada. | E63: Afeta vendas e rebalanceamento. | F63: Média | G63: Manter como pergunta ao contador, não como premissa operacional autônoma.
A64: Compensação de perdas | B64: Parcial | C64: Prejuízos não expiram e podem ser carregados indefinidamente. | D64: A legislação permite compensações sob condições e controles específicos; “indefinidamente” não deve ser afirmado sem confirmar texto vigente e transições legislativas. | E64: Afeta planejamento de alienações. | F64: Média | G64: Documentar perdas por ativo/ano e confirmar prazo e escopo com contador.
A65: Ticker ITPS na LSE | B65: Incorreto para USD | C65: Executar ITPS na LSE em USD. | D65: A listagem oficial mostra ITPS na LSE em GBP; a linha LSE em USD é IDTP, mesmo ISIN IE00B1FZSC47. | E65: Evita conversão e ordem na linha errada. | F65: Alta | G65: Para USD/LSE, usar IDTP; confirmar moeda e book antes da ordem.
A66: Tracking Difference VWRA | B66: Não sustentado | C66: TD histórico de 1–2 bps. | D66: A página oficial consultada divulga tracking error de 0,07% em 1 e 3 anos, não TD de 1–2 bps. Tracking error e tracking difference não são equivalentes. | E66: Evita falsa precisão sobre custo real. | F66: Alta | G66: Trocar por tracking error oficial ou calcular TD com séries completas.
A67: Top 10 VWRA | B67: Ajuste menor | C67: Top 10 = 24%. | D67: Com os pesos oficiais de 30/jun/2026, a soma é aproximadamente 22,7%. | E67: Concentração continua material. | F67: Alta | G67: Usar 22,7% com data-base explícita.
A68: ITPS real yield | B68: Ajuste menor | C68: Real yield = 2,24%. | D68: Página oficial em 10/ago/2026: 2,26%; variação diária é normal. | E68: Melhora precisão temporal. | F68: Alta | G68: Usar 2,26% e registrar data.
A69: IPCA | B69: Confirmado com nuance | C69: ETF em USD não protege diretamente o IPCA. | D69: Correto: ITPS protege contra inflação dos EUA, não contra inflação brasileira; câmbio pode compensar ou ampliar diferenças. | E69: Risco real em BRL permanece. | F69: Alta | G69: Gerir objetivo IPCA com ativos locais adequados, se compatível com o plano.
A70: Drawdown 2022 | B70: Confirmado no modelo | C70: Carteira teria caído 15,6%. | D70: ="Com os retornos de 2022 da pasta, 60%×"&TEXT('Cenário 1 - Buy & Hold'!C10,"0.0%")&" + 25%×"&TEXT('Cenário 1 - Buy & Hold'!D10,"0.0%")&" + 15%×"&TEXT('Cenário 1 - Buy & Hold'!E10,"0.0%")&" = "&TEXT($C$39*'Cenário 1 - Buy & Hold'!C10+$C$40*'Cenário 1 - Buy & Hold'!D10+$C$41*'Cenário 1 - Buy & Hold'!E10,"0.00%")&"." -> Com os retornos de 2022 da pasta, 60%×-18.1% + 25%×-12.7% + 15%×-10.3% = -15.56%. | E70: Confirma que o núcleo não serve como reserva de viagem de curto prazo. | F70: Alta | G70: Manter o cálculo como stress histórico do modelo, não como previsão.
A71: IOF 1,1% vs 3,5% | B71: Não confiável | C71: Classificação economizaria 2,4%. | D71: Regras de IOF-câmbio foram alteradas e disputadas em 2025; alíquotas e enquadramento devem ser confirmados no fechamento da operação. | E71: Pode mudar custo de remessa. | F71: Média-baixa | G71: Não codificar taxa fixa no modelo sem confirmação bancária e normativa atual.
A72: DCBE/CBE | B72: Confirmado em essência | C72: Obrigatório ao atingir USD 1 milhão. | D72: Banco Central mantém declaração anual para ativos externos a partir do equivalente a USD 1 milhão; há obrigação trimestral em patamar superior. | E72: Afeta compliance conforme patrimônio cresce. | F72: Alta | G72: Monitorar valor em 31/dez e regras vigentes do Banco Central.
A73: Perfil pessoal | B73: Não documentado | C73: 47 anos, economista aposentado e horizonte específico. | D73: Esses dados não constam da fonte etf-main-metrics.md nem da pasta analisada. | E73: Pode induzir suitability inadequada. | F73: Alta | G73: Confirmar diretamente com Eduardo antes de usar no parecer.
A75: PARECER FINAL
A76: A análise alternativa agrega uma narrativa econômica útil, mas deve ser tratada como rascunho de tese, não como parecer fiscal definitivo. Recomendo incorporar ao relatório apenas: (1) simplicidade dos três ETFs, (2) custo ponderado de 12,4 bps, (3) risco de concentração do VWRA, (4) papel de juros reais do ITPS e (5) diversificação hedged do AGGU. As seções tributárias, sucessórias, IOF e compliance devem permanecer como mecanismos e perguntas de diligência até validação por profissional habilitado.
A81: Fontes oficiais usadas nesta revisão: IRS (estate tax de não residentes), Lei 14.754/2023 e IN RFB 2.180/2024, Banco Central CBE, tratado Irlanda–EUA e páginas oficiais Vanguard/iShares.
A83: CENÁRIO: SEM OBJETIVO SUCESSÓRIO · PODER DE COMPRA EM USD · VIAGENS
A84: Neste cenário, a sucessão deixa de ser critério primário de seleção. O domicílio irlandês continua relevante para estrutura UCITS, mecânica de retenção no nível do fundo e classes de acumulação, mas não deve ser tratado como o motivo central do portfólio. O objetivo passa a exigir duas carteiras mentais: uma reserva líquida em USD para viagens próximas e um núcleo de longo prazo para preservar e ampliar poder de compra em dólar. Os três ETFs podem compor o núcleo, mas nenhum deles deve ser confundido com caixa: em 2022, a combinação 60/25/15 teria recuado aproximadamente 15,58%.
A89: Prioridade | B89: Horizonte | C89: Instrumento / sleeve | D89: VWRA | E89: ITPS / IDTP | F89: AGGU | G89: Decisão prática
A90: 1. Liquidez para viagens | B90: 0–24 meses | C90: Reserva separada em USD, de alta liquidez e baixa oscilação | D90: Não usar | E90: Não usar como caixa | F90: Não usar como caixa | G90: Separar despesas planejadas antes de investir o excedente no núcleo.
A91: 2. Estabilidade em USD | B91: 2–5 anos | C91: Renda fixa de menor volatilidade e duração compatível | D91: Baixa participação | E91: Protege US CPI, mas duração 6,55 anos | F91: Hedged USD, duração 6,08 anos | G91: ITPS e AGGU ainda podem cair quando juros sobem; não garantem principal no prazo.
A92: 3. Crescimento real | B92: Mais de 5 anos | C92: Núcleo diversificado | D92: Motor de crescimento | E92: Âncora de juros reais | F92: Diversificador de bonds | G92: O peso de VWRA deve refletir tolerância a perdas temporárias.
A93: 4. Sucessão | B93: Não prioritária | C93: Critério secundário | D93: Neutro | E93: Neutro | F93: Neutro | G93: Não pagar complexidade adicional exclusivamente por um objetivo sucessório inexistente.
A94: 5. Execução | B94: Em cada ordem | C94: Moeda e book da LSE | D94: VWRA em USD | E94: IDTP em USD; ITPS em GBP | F94: AGGU em USD | G94: Confirmar ticker, moeda, spread e prêmio/desconto sobre NAV.
A96: DIAGNÓSTICO DO MODELO ATUAL
A97: Métrica | B97: Fórmula / base | C97: Resultado | D97: Interpretação | E97: Limitação | F97: Status | G97: Implicação
A98: Drawdown do modelo em 2022 | B98: 60% VWRA + 25% ITPS + 15% AGGU | C98: =$C$39*'Cenário 1 - Buy & Hold'!C10+$C$40*'Cenário 1 - Buy & Hold'!D10+$C$41*'Cenário 1 - Buy & Hold'!E10 -> -0.15562 | D98: Queda material para capital destinado a viagens próximas. | E98: Um único ano histórico; não é pior caso garantido. | F98: Alto risco de prazo | G98: Criar reserva de viagens fora do núcleo.
A99: TER do núcleo | B99: Modelo 60/25/15 | C99: =$B$11 -> 0.00124 | D99: Custo explícito baixo. | E99: Não inclui spread, câmbio ou tributação. | F99: Eficiente | G99: Manter foco em custo total de execução.
A100: Duração da renda fixa | B100: ITPS + AGGU ponderados | C100: =$D$11 -> 6.37375 | D100: Sensibilidade relevante a juros. | E100: Duração não representa prazo garantido de resgate. | F100: Intermediária | G100: Não usar como caixa para viagem próxima.
A102: RECOMENDAÇÃO CONDICIONAL
A103: Primeiro, separe em USD o valor das viagens previstas para os próximos 12–24 meses, acrescido de uma margem operacional; esse montante não deve depender de VWRA, ITPS/IDTP ou AGGU para estar disponível na data da viagem. Depois, aplique somente o capital excedente no núcleo 60/25/15 ou em uma versão mais conservadora, conforme tolerância ao drawdown. Sem o orçamento anual de viagens e a data do primeiro uso, não é tecnicamente correto recomendar uma nova alocação exata. Para ordens em USD na LSE, use IDTP — não ITPS — para a classe de TIPS identificada pelo ISIN IE00B1FZSC47.
A108: DADOS A CONFIRMAR PARA DEFINIR A ALOCAÇÃO: orçamento anual de viagens em USD; data da primeira retirada; reserva já existente em USD; perda temporária máxima aceitável.
A110: COMPARAÇÃO COM A NOTA “INVESTMENT COMMITTEE / FAMILY OFFICE”
A111: Parecer: a nota institucional melhora substancialmente o enquadramento — mandato, função econômica, orçamento de risco e governança — e deve ser incorporada como linguagem de comitê. Entretanto, sua principal correção factual está invertida: o OCF vigente do VWRA é 0,14%, não 0,19%. A página oficial atual informa redução de 19 para 14 bps; portanto, o TER ponderado de 0,124% e o custo anual de USD 248 do modelo permanecem corretos. A nota também usa uma fotografia diferente para AGGU e omite um sleeve de liquidez, indispensável para o objetivo declarado de viagens.
A116: Tema | B116: Veredito | C116: Nota institucional | D116: Dado oficial / pasta | E116: Diferença | F116: Impacto no mandato | G116: Decisão
A117: Enquadramento de comitê | B117: Incorporar | C117: Prioriza mandato, função, risco e implementação. | D117: Mais robusto que uma comparação centrada em produto. | E117: Melhoria qualitativa | F117: Eleva governança e clareza de papéis. | G117: Adotar a estrutura narrativa.
A118: Funções econômicas | B118: Confirmado | C118: VWRA = crescimento; AGGU = estabilidade; ITPS = inflação. | D118: Compatível com a matriz atual, com ressalva de que “estabilidade” não significa principal estável. | E118: Sem conflito material | F118: Útil para monitoramento por sleeve. | G118: Adotar “diversificador defensivo” para AGGU.
A119: OCF do VWRA | B119: Incorreto | C119: Afirma 0,19% e diz que 0,14% estaria errado. | D119: Vanguard atual: redução de 19 para 14 bps; fonte da pasta registra 0,14%. | E119: +5 bps no VWRA | F119: Superestima o custo do modelo em 3 bps. | G119: Manter 0,14%.
A120: TER do modelo 60/25/15 | B120: Confirmado na pasta | C120: Com 0,19%, custo seria maior. | D120: Com OCF atual: 0,124% e USD 248/ano sobre USD 200 mil. | E120: USD 60/ano | F120: Não altera a arquitetura, mas afeta precisão. | G120: Manter os KPIs atuais.
A121: VWRA: estrutura e concentração | B121: Confirmado | C121: 3.782 ações, P/E 23,2x, EUA 61,7%, tracking error 0,07%. | D121: Coincide com dados oficiais de 30/jun/2026. | E121: Sem conflito | F121: Risco dominante continua sendo equity/valuation. | G121: Incorporar a leitura institucional.
A122: NAV do VWRA | B122: Data divergente | C122: USD 194,35 em referência próxima a 10/ago. | D122: Pasta possui USD 190,57 com data explícita de 03/ago para a classe Acc. | E122: Fotografias distintas | F122: NAV muda diariamente e não define mérito estratégico. | G122: Atualizar somente imediatamente antes da ordem.
A123: AGGU: métricas correntes | B123: Atualizar | C123: 19.979; YTM 4,02%; duração 6,06; NAV 5,81; YTD 0,25%. | D123: Issuer em 07/ago: 19.980; YTM 3,97%; duração 6,08; NAV 5,83; YTD 0,51%. | E123: Pequenas diferenças de snapshot | F123: Não muda a função, mas exige consistência de data. | G123: Manter snapshot oficial de 07/ago.
A124: ITPS: métricas correntes | B124: Confirmado | C124: 48 posições; YTM 4,54%; real yield 2,26%; duração 6,55. | D124: Coincide com issuer em 10/ago/2026. | E124: Sem conflito | F124: Especialista em US CPI, não caixa. | G124: Manter.
A125: Ticker de execução do TIPS | B125: Omissão relevante | C125: Usa ITPS sob framework USD. | D125: ITPS é a linha LSE em GBP; IDTP é a linha LSE em USD, mesmo ISIN. | E125: Risco operacional | F125: Pode gerar execução na moeda errada. | G125: Usar IDTP para ordens em USD.
A126: Perfis estratégicos | B126: Úteis, não completos | C126: Oferece quatro alocações 100% em ETFs. | D126: Não inclui caixa/reserva de viagens. | E126: Falha de adequação ao objetivo | F126: Mesmo o perfil defensivo pode sofrer perda material. | G126: Adicionar sleeve líquido antes dos ETFs.
A127: Risk map | B127: Incorporar com nuance | C127: Classifica riscos por sleeve. | D127: Coerente, mas AGGU e ITPS mantêm drawdown e duração próximos de seis anos. | E127: Ajuste semântico | F127: Evita interpretar bonds como garantia de capital. | G127: Adotar com legendas e horizonte.
A128: Conclusão “sem desqualificador” | B128: Concordância parcial | C128: Aprova os três para próxima etapa. | D128: Nenhum problema estrutural; falta definir liquidez, horizonte e drawdown aceitável. | E128: Gate de suitability pendente | F128: Seleção dos ETFs está avançada; alocação ainda não. | G128: Aprovar veículos, não a alocação final.
A130: STRESS DOS QUATRO PERFIS PROPOSTOS — RETORNOS DE 2022 DA PASTA
A131: Perfil | B131: VWRA | C131: AGGU | D131: ITPS | E131: Retorno 2022 | F131: Leitura para viagens | G131: Status
A132: Growth | B132: 0.7 | C132: 0.2 | D132: 0.1 | E132: =B132*'Cenário 1 - Buy & Hold'!C10+C132*'Cenário 1 - Buy & Hold'!E10+D132*'Cenário 1 - Buy & Hold'!D10 -> -0.15979 | F132: Inadequado para despesas próximas | G132: Núcleo longo prazo
A133: Balanced Growth | B133: 0.6 | C133: 0.3 | D133: 0.1 | E133: =B133*'Cenário 1 - Buy & Hold'!C10+C133*'Cenário 1 - Buy & Hold'!E10+D133*'Cenário 1 - Buy & Hold'!D10 -> -0.15202 | F133: Inadequado para despesas próximas | G133: Núcleo longo prazo
A134: Balanced / Defensive | B134: 0.5 | C134: 0.4 | D134: 0.1 | E134: =B134*'Cenário 1 - Buy & Hold'!C10+C134*'Cenário 1 - Buy & Hold'!E10+D134*'Cenário 1 - Buy & Hold'!D10 -> -0.14425 | F134: Ainda sujeito a perda de dois dígitos | G134: Núcleo longo prazo
A135: Defensive | B135: 0.4 | C135: 0.45 | D135: 0.15 | E135: =B135*'Cenário 1 - Buy & Hold'!C10+C135*'Cenário 1 - Buy & Hold'!E10+D135*'Cenário 1 - Buy & Hold'!D10 -> -0.13768 | F135: Ainda sujeito a perda de dois dígitos | G135: Núcleo longo prazo
A137: CONCLUSÃO DA COMPARAÇÃO
A138: A nota deve substituir o tom de “comparação de ETFs” por uma arquitetura de funções econômicas, mas não deve substituir os dados vigentes da pasta. OCF do VWRA: 0,14%. AGGU: manter o snapshot coerente de 07/ago/2026. ITPS: métricas confirmadas, com IDTP como ticker USD na LSE. Para este mandato específico, a próxima etapa não é escolher entre quatro carteiras integralmente investidas: é quantificar primeiro a reserva de viagens em USD e somente depois selecionar o perfil do capital excedente.
A143: GATE PARA PRÓXIMA ETAPA: informar orçamento anual de viagens em USD, data da primeira retirada, reserva líquida existente e drawdown máximo tolerável.

Sheet Dashboard Visual
A1: PAINEL DE ANÁLISE — RETORNO REAL LÍQUIDO DE ETF IRLANDÊS (2019–2026)
A2: Análise Visual de Retorno Real Líquido, Impacto da Inflação e Comparação Tática de Cenários (2019 - 2026)
A4: 1. INDICADORES CHAVE DE DESEMPENHO LÍQUIDO FINAL (MAIO 2026)
A5: Métrica Líquida Final | B5: Cenário 1: Buy & Hold (Diferimento) | C5: Cenário 2: Rebalanceamento (2021) | D5: Vantagem Real (C1 - C2) | E5: Ganho (%) | F5: Análise de Eficiência
A6: Patrimônio Líquido Nominal (USD Equiv.) | B6: ='Comparativo de Cenários'!B13 -> 370581.78 | C6: ='Comparativo de Cenários'!C13 -> 359230.27 | D6: =B6-C6 -> 11351.514 | E6: =IFERROR(D6/B6, 0) -> 0.030631603 | F6: Saldo final líquido de imposto brasileiro mantido em USD na IBKR.
A7: Patrimônio Líquido Real USD (CPI-adj) | B7: ='Comparativo de Cenários'!B21 -> 284916.2 | C7: ='Comparativo de Cenários'!C21 -> 275977.24 | D7: =B7-C7 -> 8938.9649 | E7: =IFERROR(D7/B7, 0) -> 0.031374014 | F7: Poder de compra real final líquido na conta americana (t0 = 2019).
A8: Patrimônio Líquido Nominal (BRL) | B8: ='Comparativo de Cenários'!B12 -> 1910349.1 | C8: ='Comparativo de Cenários'!C12 -> 1851832 | D8: =B8-C8 -> 58517.055 | E8: =IFERROR(D8/B8, 0) -> 0.030631603 | F8: Valor líquido total convertido pelo câmbio de venda PTAX 5,1550.
A9: Patrimônio Líquido Real BRL (IPCA-adj) | B9: ='Comparativo de Cenários'!B20 -> 1292404.3 | C9: ='Comparativo de Cenários'!C20 -> 1250830.2 | D9: =B9-C9 -> 41574.062 | E9: =IFERROR(D9/B9, 0) -> 0.032168 | F9: Poder de compra líquido real final no Brasil (t0 = 2019).
A10: Retorno Líquido Real USD Acumulado (%) | B10: ='Comparativo de Cenários'!B22 -> 0.42458102 | C10: ='Comparativo de Cenários'!C22 -> 0.37988619 | D10: =B10-C10 -> 0.044694825 | E10: =B10-C10 -> 0.044694825 | F10: Retorno composto real (descontados impostos e inflação US CPI).
A11: Retorno Líquido Real BRL Acumulado (%) | B11: ='Comparativo de Cenários'!B23 -> 0.66770454 | C11: ='Comparativo de Cenários'!C23 -> 0.61405782 | D11: =B11-C11 -> 0.05364672 | E11: =B11-C11 -> 0.05364672 | F11: Retorno composto real (descontados impostos e inflação IPCA).
A12: Total de Impostos Nominais Pagos (BRL) | B12: ='Comparativo de Cenários'!B11 -> 200362.78 | C12: ='Comparativo de Cenários'!C11 -> 190036.24 | D12: =C12-B12 -> -10326.539 | E12: =IFERROR(D12/C12, 0) -> -0.054339841 | F12: Total de IR pago (Cenário 1 diferiu tudo; Cenário 2 pagou em 2021/2026).
A13: Total de Impostos Reais Pagos (BRL em t0) | B13: ='Comparativo de Cenários'!B18 -> 135551 | C13: ='Comparativo de Cenários'!C18 -> 130550.45 | D13: =C13-B13 -> -5000.5451 | E13: =IFERROR(D13/C13, 0) -> -0.038303545 | F13: Total de impostos trazidos a valor real de t0 (2019) descontando IPCA.
A14: 2. INDICADORES CHAVE DE DESEMPENHO LÍQUIDO FINAL - APORTES RECORRENTES (MAIO/2026)
A15: Métrica Líquida Final | B15: Cenário A: +USD 5k / Trimestre | C15: Cenário B: +USD 10k / Trimestre | D15: Vantagem Real (B - A) | E15: Ganho (%) | F15: Análise de Eficiência
A16: Patrimônio Líquido Nominal (USD Equiv.) | B16: ='Aportes Trimestrais'!B48 -> 538579.26 | C16: ='Aportes Trimestrais'!F48 -> 724146.45 | D16: =C16-B16 -> 185567.19 | E16: =(C16-B16)/B16 -> 0.34454946 | F16: Saldo final líquido de imposto brasileiro mantido em USD na IBKR.
A17: Patrimônio Líquido Real USD (CPI-adj) | B17: ='Aportes Trimestrais'!C48 -> 414100.62 | C17: ='Aportes Trimestrais'!G48 -> 556778.76 | D17: =C17-B17 -> 142678.14 | E17: =(C17-B17)/B17 -> 0.34454946 | F17: Poder de compra real final líquido na conta americana (t0 = 2019).
A18: Patrimônio Líquido Nominal (BRL) | B18: ='Aportes Trimestrais'!B47 -> 2776376.1 | C18: ='Aportes Trimestrais'!F47 -> 3732975 | D18: =C18-B18 -> 956598.87 | E18: =(C18-B18)/B18 -> 0.34454946 | F18: Valor líquido total convertido pelo câmbio de venda PTAX 5,1550.
A19: Patrimônio Líquido Real BRL (IPCA-adj) | B19: ='Aportes Trimestrais'!C47 -> 1878214.1 | C19: ='Aportes Trimestrais'!G47 -> 2525351.8 | D19: =C19-B19 -> 647137.65 | E19: =(C19-B19)/B19 -> 0.34454946 | F19: Poder de compra líquido real final no Brasil (t0 = 2019).
A20: Retorno Líquido Real USD Acumulado (%) | B20: ='Aportes Trimestrais'!C49 -> 0.45947174 | C20: ='Aportes Trimestrais'!G49 -> 0.41585539 | D20: =C20-B20 -> -0.043616356 | E20: =C20-B20 -> -0.043616356 | F20: Retorno composto real (descontados impostos e inflação US CPI).
A21: Retorno Líquido Real BRL Acumulado (%) | B21: ='Aportes Trimestrais'!C50 -> 0.87089198 | C21: ='Aportes Trimestrais'!G50 -> 0.70221482 | D21: =C21-B21 -> -0.16867716 | E21: =C21-B21 -> -0.16867716 | F21: Retorno composto real (descontados impostos e inflação IPCA).
A22: Total de Impostos Nominais Pagos (BRL) | B22: ='Aportes Trimestrais'!B46 -> 228068.97 | C22: ='Aportes Trimestrais'!F46 -> 271758.44 | D22: =C22-B22 -> 43689.463 | E22: =(C22-B22)/B22 -> 0.1915625 | F22: Total de IR pago (Lei 14.754/2023, 15% sobre o ganho de capital).
A23: Total de Impostos Reais Pagos (BRL em t0) | B23: ='Aportes Trimestrais'!C46 -> 154288.31 | C23: ='Aportes Trimestrais'!G46 -> 183844.16 | D23: =C23-B23 -> 29555.854 | E23: =(C23-B23)/B23 -> 0.1915625 | F23: Custo tributário real trazido a valor presente de 2019 pelo IPCA.
A26: 3. MATRIZ DE ALOCAÇÃO DE ATIVOS (PORTFÓLIO MODELO - REAL CORE)
A27: Classe de Ativo | B27: Ticker | C27: Bolsa / Domicílio | D27: ISIN | E27: Peso-Alvo (%) | F27: Custo Inicial (USD) | G27: Custo Inicial (BRL) | H27: Papel Estrutural na Carteira
A28: Ações Globais (Desenvolvidos & Emergentes) | B28: VWRA | C28: LSE / Irlanda | D28: IE00BK5BQT80 | E28: 0.6 | F28: 120000 | G28: ='Cenário 1 - Buy & Hold'!$B$6*F28 -> 464976 | H28: Motor principal de valorização real e acúmulo no longo prazo.
A29: Títulos Soberanos EUA Indexados à Inflação | B29: ITPS | C29: LSE (GBP) / Irlanda | D29: IE00B1FZSC47 | E29: 0.25 | F29: 50000 | G29: ='Cenário 1 - Buy & Hold'!$B$6*F29 -> 193740 | H29: Proteção contra inflação dos EUA; sensível a variações dos juros reais.
A30: Renda Fixa Global (Hedged em USD) | B30: AGGU | C30: LSE / Irlanda | D30: IE00BZ043R46 | E30: 0.15 | F30: 30000 | G30: ='Cenário 1 - Buy & Hold'!$B$6*F30 -> 116244 | H30: Diversificação global de renda fixa investment grade, com hedge cambial para USD.
A31: Total do Portfólio | E31: =SUM(E28:E30) -> 1 | F31: =SUM(F28:F30) -> 200000 | G31: =SUM(G28:G30) -> 774960 | H31: Estrutura UCITS irlandesa; no cenário sem sucessão, priorizar liquidez e poder de compra em USD.
A33: 4. MATRIZ DE CORRELAÇÃO ESTIMADA DOS ATIVOS DA CARTEIRA
A34: Ativo de Referência | B34: VWRA (Ações) | C34: ITPS (TIPS) | D34: AGGU (Bonds) | E34: Análise de Diversificação Estrutural
A35: VWRA (Ações Globais) | B35: 1 | C35: 0.4 | D35: 0.25 | E35: Correlação histórica estimada; diversificação não elimina perdas conjuntas em choques inflacionários.
A36: ITPS (TIPS) | B36: 0.4 | C36: 1 | D36: 0.55 | E36: TIPS protegem contra US CPI no longo prazo, mas podem cair quando juros reais sobem.
A37: AGGU (Bonds Globais) | B37: 0.25 | C37: 0.55 | D37: 1 | E37: Bonds globais hedged em USD reduzem risco cambial, mas mantêm risco de juros e crédito.
A39: 5. DADOS AUXILIARES DOS GRÁFICOS (VINCULADOS)
A40: Cenário | B40: Nominal USD | C40: Real USD (t0)
A41: Cenário 1: Buy & Hold | B41: =B6 -> 370581.78 | C41: =B7 -> 284916.2
A42: Cenário 2: Rebalanceamento | B42: =C6 -> 359230.27 | C42: =C7 -> 275977.24
A44: Cenário | B44: Imposto Nominal BRL | C44: Imposto Real BRL (t0)
A45: Cenário 1: Buy & Hold | B45: =B12 -> 200362.78 | C45: =B13 -> 135551
A46: Cenário 2: Rebalanceamento | B46: =C12 -> 190036.24 | C46: =C13 -> 130550.45
A48: Gerado em: 2026-08-10 | v4.0 - Dashboards, Matrizes e Gráficos Embarcados | Grounded under Lei 14.754/2023

Sheet Aportes Trimestrais
A1: SIMULAÇÃO COMPARATIVA DE APORTES TRIMESTRAIS DE CAPITAL NOVO (FRESH MONEY)
A2: Análise de Rebalanceamento por Novos Aportes (Top-Up Routing) sem vendas vs. Impacto Tributário (Lei 14.754/2023) e Inflação
C4: CENÁRIO A: APORTES RECORRENTES DE USD 5k / TRIMESTRE | J4: CENÁRIO B: APORTES RECORRENTES DE USD 10k / TRIMESTRE
A5: Período | B5: Taxa PTAX | C5: VWRA (USD) | D5: ITPS (USD) | E5: AGGU (USD) | F5: Saldo (USD) | G5: Aporte (USD) | H5: Saldo (BRL) | I5: Custo (BRL) | J5: VWRA (USD) | K5: ITPS (USD) | L5: AGGU (USD) | M5: Saldo (USD) | N5: Aporte (USD) | O5: Saldo (BRL) | P5: Custo (BRL)
A6: 2019-01-02 (Compra) | B6: 3.8748 | C6: 120000 | D6: 50000 | E6: 30000 | F6: =SUM(C6:E6) -> 200000 | G6: 0 | H6: =F6*B6 -> 774960 | I6: 774960 | J6: 120000 | K6: 50000 | L6: 30000 | M6: =SUM(J6:L6) -> 200000 | N6: 0 | O6: =M6*B6 -> 774960 | P6: 774960
A7: 2019-Q1 | B7: 3.913775 | C7: 128341.65 | D7: 53476.458 | E7: 32085.945 | F7: =SUM(C7:E7) -> 213904.05 | G7: 5000 | H7: =F7*B7 -> 837172.33 | I7: 794528.87 | J7: 131341.65 | K7: 54726.458 | L7: 32835.945 | M7: =SUM(J7:L7) -> 218904.05 | N7: 10000 | O7: =M7*B7 -> 856741.2 | P7: 814097.75
A8: 2019-Q2 | B8: 3.95275 | C8: 137055.96 | D8: 57106.728 | E8: 34264.397 | F8: =SUM(C8:E8) -> 228427.08 | G8: 5000 | H8: =F8*B8 -> 902915.15 | I8: 814292.62 | J8: 143190.17 | K8: 59662.189 | L8: 35797.321 | M8: =SUM(J8:L8) -> 238649.68 | N8: 10000 | O8: =M8*B8 -> 943322.53 | P8: 853625.25
A9: 2019-Q3 | B9: 3.991725 | C9: 146157.56 | D9: 60898.943 | E9: 36540.196 | F9: =SUM(C9:E9) -> 243596.7 | G9: 5000 | H9: =F9*B9 -> 972371.04 | I9: 834251.25 | J9: 155564.36 | K9: 64818.457 | L9: 38891.622 | M9: =SUM(J9:L9) -> 259274.44 | N9: 10000 | O9: =M9*B9 -> 1034952.3 | P9: 893542.5
A10: 2019-Q4 | B10: 4.0307 | C10: 155664.99 | D10: 64860.403 | E10: 38916.279 | F10: =SUM(C10:E10) -> 259441.67 | G10: 5000 | H10: =F10*B10 -> 1045731.5 | I10: 854404.75 | J10: 168490.14 | K10: 70204.754 | L10: 42122.494 | M10: =SUM(J10:L10) -> 280817.39 | N10: 10000 | O10: =M10*B10 -> 1131890.7 | P10: 933849.5
A11: 2020-Q1 | B11: 4.3222 | C11: 163586.02 | D11: 68160.879 | E11: 40897.026 | F11: =SUM(C11:E11) -> 272643.93 | G11: 5000 | H11: =F11*B11 -> 1178421.6 | I11: 876015.75 | J11: 179816.73 | K11: 74924.5 | L11: 44954.215 | M11: =SUM(J11:L11) -> 299695.44 | N11: 10000 | O11: =M11*B11 -> 1295343.6 | P11: 977071.5
A12: 2020-Q2 | B12: 4.6137 | C12: 171758.03 | D12: 71565.598 | E12: 42939.939 | F12: =SUM(C12:E12) -> 286263.56 | G12: 5000 | H12: =F12*B12 -> 1320734.2 | I12: 899084.25 | J12: 191501.54 | K12: 79793.003 | L12: 47875.773 | M12: =SUM(J12:L12) -> 319170.32 | N12: 10000 | O12: =M12*B12 -> 1472556.1 | P12: 1023208.5
A13: 2020-Q3 | B13: 4.9052 | C13: 180188.6 | D13: 75078.315 | E13: 45046.871 | F13: =SUM(C13:E13) -> 300313.79 | G13: 5000 | H13: =F13*B13 -> 1473099.2 | I13: 923610.25 | J13: 203556.29 | K13: 84815.198 | L13: 50889.401 | M13: =SUM(J13:L13) -> 339260.89 | N13: 10000 | O13: =M13*B13 -> 1664142.5 | P13: 1072260.5
A14: 2020-Q4 | B14: 5.1967 | C14: 188884.64 | D14: 78701.885 | E14: 47221.7 | F14: =SUM(C14:E14) -> 314808.23 | G14: 5000 | H14: =F14*B14 -> 1635963.9 | I14: 949593.75 | J14: 215991.12 | K14: 89997.146 | L14: 53998.362 | M14: =SUM(J14:L14) -> 359986.63 | N14: 10000 | O14: =M14*B14 -> 1870742.5 | P14: 1124227.5
A15: 2021-Q1 | B15: 5.29265 | C15: 197390.59 | D15: 82246.744 | E15: 49347.549 | F15: =SUM(C15:E15) -> 328984.89 | G15: 5000 | H15: =F15*B15 -> 1741201.9 | I15: 976057 | J15: 228288.11 | K15: 95119.75 | L15: 57072.368 | M15: =SUM(J15:L15) -> 380480.23 | N15: 10000 | O15: =M15*B15 -> 2013748.7 | P15: 1177154
A16: 2021-Q2 | B16: 5.3886 | C16: 206144.27 | D16: 85893.62 | E16: 51536.918 | F16: =SUM(C16:E16) -> 343574.81 | G16: 5000 | H16: =F16*B16 -> 1851387.2 | I16: 1003000 | J16: 240942.16 | K16: 100393.52 | L16: 60235.557 | M16: =SUM(J16:L16) -> 401571.24 | N16: 10000 | O16: =M16*B16 -> 2163906.8 | P16: 1231040
A17: 2021-Q3 | B17: 5.48455 | C17: 215153.41 | D17: 89648.01 | E17: 53788.584 | F17: =SUM(C17:E17) -> 358590.01 | G17: 5000 | H17: =F17*B17 -> 1966704.8 | I17: 1030422.7 | J17: 253965.75 | K17: 105819.68 | L17: 63491.616 | M17: =SUM(J17:L17) -> 423277.05 | N17: 10000 | O17: =M17*B17 -> 2321484.2 | P17: 1285885.5
... A36: 2026-May29 | B36: 5.155 | C36: 368954.8 | D36: 135916.29 | E36: 77950.454 | F36: =SUM(C36:E36) -> 582821.55 | G36: 0 | H36: =F36*B36 -> 3004445.1 | I36: 1483985.2 | J36: 471263.89 | K36: 191482.94 | L36: 114117.06 | M36: =SUM(J36:L36) -> 776863.9 | N36: 0 | O36: =M36*B36 -> 4004733.4 | P36: 2193010.5
A38: 2. MEMORANDO DE LIQUIDAÇÃO FISCAL E RETORNOS REAIS DESCONTADOS PELA INFLAÇÃO
A39: Métrica de Comparação Final (Venda em Maio/2026) | B39: Cenário A: +USD 5k / Trimestre | F39: Cenário B: +USD 10k / Trimestre
B40: Nominal | C40: Real (t0) | D40: Retorno (%) | E40: Análise Fiscal & Econômica | F40: Nominal | G40: Real (t0) | H40: Retorno (%) | I40: Análise Fiscal & Econômica
A41: Valor Final da Carteira (USD) | B41: =F36 -> 582821.55 | C41: =B41/$B$54 -> 448117.44 | D41: =(B41-B43)/B43 -> 0.68933781 | E41: Total acumulado na conta americana. | F41: =M36 -> 776863.9 | G41: =F41/$B$54 -> 597311.93 | H41: =(F41-F43)/F43 -> 0.58543653 | I41: Total acumulado na conta americana.
A42: Valor Final da Carteira (BRL) | B42: =H36 -> 3004445.1 | C42: =B42/$B$55 -> 2032502.4 | D42: =(B42-B44)/B44 -> 1.0245788 | E42: Total convertido pela PTAX de venda. | F42: =O36 -> 4004733.4 | G42: =F42/$B$55 -> 2709195.9 | H42: =(F42-F44)/F44 -> 0.82613508 | I42: Total convertido pela PTAX de venda.
A43: Total de Capital Contribuído (USD) | B43: =200000+SUM(G7:G36) -> 345000 | C43: 283733.22 | E43: Capital inicial + 29 aportes. | F43: =200000+SUM(N7:N36) -> 490000 | G43: 393245.5 | I43: Capital inicial + 29 aportes.
A44: Custo de Aquisição Declarado (BRL) | B44: =I36 -> 1483985.2 | C44: =B44/$B$55 -> 1003913.7 | E44: Custo contábil para imposto de renda. | F44: =P36 -> 2193010.5 | G44: =F44/$B$55 -> 1483568.2 | I44: Custo contábil para imposto de renda.
A45: Ganho de Capital Tributável (BRL) | B45: =B42-B44 -> 1520459.8 | C45: =B45/$B$55 -> 1028588.7 | E45: Ganho sujeito à tributação brasileira. | F45: =F42-F44 -> 1811722.9 | G45: =F45/$B$55 -> 1225627.7 | I45: Ganho sujeito à tributação brasileira.
A46: Imposto de Renda Devido (BRL - 15%) | B46: =B45*$B$53 -> 228068.97 | C46: =B46/$B$55 -> 154288.31 | E46: Apuração de 15% sob a Lei 14.754/2023. | F46: =F45*$B$53 -> 271758.44 | G46: =F46/$B$55 -> 183844.16 | I46: Apuração de 15% sob a Lei 14.754/2023.
A47: Patrimônio Líquido Final (BRL) | B47: =B42-B46 -> 2776376.1 | C47: =B47/$B$55 -> 1878214.1 | E47: Patrimônio líquido real no Brasil. | F47: =F42-F46 -> 3732975 | G47: =F47/$B$55 -> 2525351.8 | I47: Patrimônio líquido real no Brasil.
A48: Patrimônio Líquido Final (USD Equiv.) | B48: =B47/$B$56 -> 538579.26 | C48: =B48/$B$54 -> 414100.62 | E48: Patrimônio líquido na conta da IBKR. | F48: =F47/$B$56 -> 724146.45 | G48: =F48/$B$54 -> 556778.76 | I48: Patrimônio líquido na conta da IBKR.
A49: Retorno Absoluto Líquido USD (%) | B49: =(B48-B43)/B43 -> 0.56109931 | C49: =(C48-C43)/C43 -> 0.45947174 | E49: Retorno líquido de inflação (US CPI) e IR. | F49: =(F48-F43)/F43 -> 0.47784991 | G49: =(G48-G43)/G43 -> 0.41585539 | I49: Retorno líquido de inflação (US CPI) e IR.
A50: Retorno Absoluto Líquido BRL (%) | B50: =(B47-B44)/B44 -> 0.87089198 | C50: =(C47-C44)/C44 -> 0.87089198 | E50: Retorno líquido de inflação (IPCA) e IR. | F50: =(F47-F44)/F44 -> 0.70221482 | G50: =(G47-G44)/G44 -> 0.70221482 | I50: Retorno líquido de inflação (IPCA) e IR.
A52: Premissas (inputs)
A53: Alíquota IR (Lei 14.754/2023) | B53: 0.15
A54: US CPI Acum. 2019-2026 | B54: 1.3006
A55: IPCA Acum. 2019-2026 | B55: 1.4782
A56: PTAX de venda (mai/2026) | B56: 5.155

Sheet Comparativo de Cenários
A1: SIMULAÇÃO COMPARATIVA DE CENÁRIOS DE REBALANCEAMENTO (NOMINAL E REAL)
A2: Análise de impacto fiscal, custo de oportunidade e retornos descontados pela inflação oficial (US CPI e IPCA)
A4: COMPARAÇÃO DE RESULTADOS FINAIS (LIQUIDAÇÃO EM MAIO 2026)
A5: Métrica | B5: Cenário 1: Buy & Hold (Diferimento) | C5: Cenário 2: Rebalanceamento em 2021 | D5: Diferença Absoluta | E5: Diferença (%) | F5: Análise de Impacto de Longo Prazo
A6: Valor Final da Carteira Nominal (USD) | B6: ='Cenário 1 - Buy & Hold'!B17 -> 409449.44 | C6: ='Cenário 2 - Rebalanceamento'!B23 -> 396094.72 | D6: =C6-B6 -> -13354.723 | E6: =D6/B6 -> -0.032616292 | F6: O rebalanceamento vendeu ações (VWRA) para comprar bonds, reduzindo o patrimônio final bruto em USD.
A7: Valor Final da Carteira Nominal (BRL) | B7: ='Cenário 1 - Buy & Hold'!E17 -> 2110711.9 | C7: ='Cenário 2 - Rebalanceamento'!E23 -> 2041868.3 | D7: =C7-B7 -> -68843.595 | E7: =D7/B7 -> -0.032616292 | F7: Reflete a desvalorização cambial acumulada do Real, ampliando o ganho medido em moeda local.
A8: Custo de Aquisição Final Declarado (BRL) | B8: ='Cenário 1 - Buy & Hold'!E18 -> 774960 | C8: ='Cenário 2 - Rebalanceamento'!B24 -> 859353.5 | D8: =C8-B8 -> 84393.499 | E8: =D8/B8 -> 0.10890046 | F8: O rebalanceamento de 2021 ao câmbio alto de 5,5805 gerou um 'Basis Bump' legal no custo contábil do Cenário 2.
A9: Imposto de Renda Pago em 2021 (BRL) | B9: 0 | C9: ='Cenário 2 - Rebalanceamento'!E20 -> 12659.025 | D9: =C9-B9 -> 12659.025 | E9: =IFERROR(D9/B9,"n/a") -> n/a | F9: Cenário 2 pagou imposto de 15% na venda de ações para rebalancear. Cenário 1 diferiu 100%.
A10: Imposto de Renda Pago em 2026 (BRL) | B10: ='Cenário 1 - Buy & Hold'!B20 -> 200362.78 | C10: ='Cenário 2 - Rebalanceamento'!B26 -> 177377.22 | D10: =C10-B10 -> -22985.564 | E10: =D10/B10 -> -0.11471973 | F10: Liquidação final. Cenário 2 paga menos IR em 2026 por conta do custo de aquisição mais elevado (Basis Bump).
A11: Total de Impostos Nominais Pagos (BRL) | B11: ='Cenário 1 - Buy & Hold'!B20 -> 200362.78 | C11: ='Cenário 2 - Rebalanceamento'!E26 -> 190036.24 | D11: =C11-B11 -> -10326.539 | E11: =D11/B11 -> -0.051539209 | F11: No total absoluto nominal, o Cenário 2 pagou menos imposto devido à elevação do custo contábil em BRL.
A12: Patrimônio Líquido Final Nominal (BRL) | B12: ='Cenário 1 - Buy & Hold'!E17-'Cenário 1 - Buy & Hold'!B20 -> 1910349.1 | C12: ='Cenário 2 - Rebalanceamento'!E23-'Cenário 2 - Rebalanceamento'!E26 -> 1851832 | D12: =C12-B12 -> -58517.055 | E12: =D12/B12 -> -0.030631603 | F12: O custo de oportunidade de vender ações em 2021 superou de longe a economia fiscal nominal gerada.
A13: Patrimônio Líquido Final Nominal (USD Equiv.) | B13: =('Cenário 1 - Buy & Hold'!E17-'Cenário 1 - Buy & Hold'!B20)/'Cenário 1 - Buy & Hold'!B14 -> 370581.78 | C13: =('Cenário 2 - Rebalanceamento'!E23-'Cenário 2 - Rebalanceamento'!E26)/'Cenário 2 - Rebalanceamento'!B15 -> 359230.27 | D13: =C13-B13 -> -11351.514 | E13: =D13/B13 -> -0.030631603 | F13: O investidor terminou com USD 11,3k adicionais na conta americana da IBKR no Cenário 1 (Buy & Hold).
A14: Retorno Absoluto USD Líquido Nominal (%) | B14: =(B13-200000)/200000 -> 0.85290892 | C14: =(C13-200000)/200000 -> 0.79615135 | D14: =C14-B14 -> -0.056757571 | E14: =C14-B14 -> -0.056757571 | F14: Retorno nominal líquido sobre o capital inicial em USD de primeira trancha.
A15: Retorno Absoluto BRL Líquido Nominal (%) | B15: =(B12-774960)/774960 -> 1.4650938 | C15: =(C12-774960)/774960 -> 1.389584 | D15: =C15-B15 -> -0.075509775 | E15: =C15-B15 -> -0.075509775 | F15: Retorno nominal líquido medido contra o custo inicial em BRL.
A16: Valor Final da Carteira Real (USD - CPI-adj) | B16: ='Cenário 1 - Buy & Hold'!B23 -> 314799.02 | C16: ='Cenário 2 - Rebalanceamento'!B29 -> 304531.44 | D16: =C16-B16 -> -10267.577 | E16: =D16/B16 -> -0.032616292 | F16: O poder de compra final real do portfólio brutificado em dólares (em termos de 2019).
A17: Valor Final da Carteira Real (BRL - IPCA-adj) | B17: ='Cenário 1 - Buy & Hold'!E23 -> 1427955.3 | C17: ='Cenário 2 - Rebalanceamento'!E29 -> 1381380.7 | D17: =C17-B17 -> -46574.607 | E17: =D17/B17 -> -0.032616292 | F17: O poder de compra final real brutificado em Reais (em termos de 2019).
A18: Total de Impostos Reais Pagos (BRL em t0) | B18: ='Cenário 1 - Buy & Hold'!B26 -> 135551 | C18: ='Cenário 2 - Rebalanceamento'!B32 -> 130550.45 | D18: =C18-B18 -> -5000.5451 | E18: =D18/B18 -> -0.036890508 | F18: O valor real do imposto pago, trazido para t0 (2019) descontado pelo IPCA.
A19: Total de Impostos Reais Pagos (USD em t0) | B19: ='Cenário 1 - Buy & Hold'!E26 -> 29882.812 | C19: ='Cenário 2 - Rebalanceamento'!E32 -> 28554.2 | D19: =C19-B19 -> -1328.6117 | E19: =D19/B19 -> -0.044460731 | F19: O valor real do imposto pago, trazido para t0 (2019) descontado pelo US CPI.
A20: Patrimônio Líquido Final Real (BRL em t0) | B20: ='Cenário 1 - Buy & Hold'!B27 -> 1292404.3 | C20: ='Cenário 2 - Rebalanceamento'!B33 -> 1250830.2 | D20: =C20-B20 -> -41574.062 | E20: =D20/B20 -> -0.032168 | F20: O poder de compra líquido de impostos e inflação real no Brasil (em termos de 2019).
A21: Patrimônio Líquido Final Real (USD em t0) | B21: ='Cenário 1 - Buy & Hold'!E27 -> 284916.2 | C21: ='Cenário 2 - Rebalanceamento'!E33 -> 275977.24 | D21: =C21-B21 -> -8938.9649 | E21: =D21/B21 -> -0.031374014 | F21: O poder de compra líquido de impostos e inflação real nos EUA (em termos de 2019).
A22: Retorno Líquido Real USD Acumulado (%) | B22: =(B21-200000)/200000 -> 0.42458102 | C22: =(C21-200000)/200000 -> 0.37988619 | D22: =C22-B22 -> -0.044694825 | E22: =C22-B22 -> -0.044694825 | F22: Retorno real líquido de impostos e inflação americana acumulado de 2019 a 2026.
A23: Retorno Líquido Real BRL Acumulado (%) | B23: =(B20-774960)/774960 -> 0.66770454 | C23: =(C20-774960)/774960 -> 0.61405782 | D23: =C23-B23 -> -0.05364672 | E23: =C23-B23 -> -0.05364672 | F23: Retorno real líquido de impostos e inflação brasileira acumulado de 2019 a 2026.

Sheet Cenário 1 - Buy & Hold
A1: CENÁRIO 1: ESTRATÉGIA BUY & HOLD (DIFERIMENTO INTEGRAL)
A2: Evolução anual e liquidação tributária nominal/real em maio de 2026 - Sem rebalanceamentos intermediários
A4: 1. EVOLUÇÃO DO PORTFÓLIO, CAMBIO E INFLAÇÃO
A5: Período | B5: PTAX Câmbio | C5: Retorno VWRA | D5: Retorno ITPS | E5: Retorno AGGU | F5: VWRA (USD) | G5: ITPS (USD) | H5: AGGU (USD) | I5: Saldo Total (USD) | J5: US CPI Anual (%) | K5: US CPI Acum. | L5: Saldo Real USD | M5: Saldo Total (BRL) | N5: IPCA Anual (%) | O5: IPCA Acum. | P5: Saldo Real BRL
A6: 2019-01-02 (Compra) | B6: 3.8748 | F6: 120000 | G6: 50000 | H6: 30000 | I6: =F6+G6+H6 -> 200000 | J6: 0 | K6: 1 | L6: =I6/K6 -> 200000 | M6: =I6*B6 -> 774960 | N6: 0 | O6: 1 | P6: =M6/O6 -> 774960
A7: 2019-12-31 | B7: 4.0307 | C7: 0.266 | D7: 0.084 | E7: 0.082 | F7: =F6*(1+C7) -> 151920 | G7: =G6*(1+D7) -> 54200 | H7: =H6*(1+E7) -> 32460 | I7: =F7+G7+H7 -> 238580 | J7: 0.0181 | K7: =K6*(1+J7) -> 1.0181 | L7: =I7/K7 -> 234338.47 | M7: =I7*B7 -> 961644.41 | N7: 0.0431 | O7: =O6*(1+N7) -> 1.0431 | P7: =M7/O7 -> 921910.08
A8: 2020-12-31 | B8: 5.1967 | C8: 0.162 | D8: 0.11 | E8: 0.056 | F8: =F7*(1+C8) -> 176531.04 | G8: =G7*(1+D8) -> 60162 | H8: =H7*(1+E8) -> 34277.76 | I8: =F8+G8+H8 -> 270970.8 | J8: 0.0136 | K8: =K7*(1+J8) -> 1.0319462 | L8: =I8/K8 -> 262582.3 | M8: =I8*B8 -> 1408154 | N8: 0.0452 | O8: =O7*(1+N8) -> 1.0902481 | P8: =M8/O8 -> 1291590.4
A9: 2021-12-31 | B9: 5.5805 | C9: 0.185 | D9: 0.06 | E9: -0.014 | F9: =F8*(1+C9) -> 209189.28 | G9: =G8*(1+D9) -> 63771.72 | H9: =H8*(1+E9) -> 33797.871 | I9: =F9+G9+H9 -> 306758.87 | J9: 0.047 | K9: =K8*(1+J9) -> 1.0804476 | L9: =I9/K9 -> 283918.32 | M9: =I9*B9 -> 1711867.9 | N9: 0.1006 | O9: =O8*(1+N9) -> 1.1999271 | P9: =M9/O9 -> 1426643.3
A10: 2022-12-31 | B10: 5.2177 | C10: -0.1807 | D10: -0.127 | E10: -0.103 | F10: =F9*(1+C10) -> 171388.78 | G10: =G9*(1+D10) -> 55672.712 | H10: =H9*(1+E10) -> 30316.691 | I10: =F10+G10+H10 -> 257378.18 | J10: 0.08 | K10: =K9*(1+J10) -> 1.1668834 | L10: =I10/K10 -> 220568.89 | M10: =I10*B10 -> 1342922.1 | N10: 0.0579 | O10: =O9*(1+N10) -> 1.2694029 | P10: =M10/O10 -> 1057916.4
A11: 2023-12-31 | B11: 4.8413 | C11: 0.222 | D11: 0.039 | E11: 0.071 | F11: =F10*(1+C11) -> 209437.09 | G11: =G10*(1+D11) -> 57843.947 | H11: =H10*(1+E11) -> 32469.176 | I11: =F11+G11+H11 -> 299750.21 | J11: 0.0412 | K11: =K10*(1+J11) -> 1.214959 | L11: =I11/K11 -> 246716.31 | M11: =I11*B11 -> 1451180.7 | N11: 0.0462 | O11: =O10*(1+N11) -> 1.3280493 | P11: =M11/O11 -> 1092716
A12: 2024-12-31 | B12: 4.8023 | C12: 0.201 | D12: 0.012 | E12: 0.042 | F12: =F11*(1+C12) -> 251533.94 | G12: =G11*(1+D12) -> 58538.075 | H12: =H11*(1+E12) -> 33832.881 | I12: =F12+G12+H12 -> 343904.9 | J12: 0.029 | K12: =K11*(1+J12) -> 1.2501928 | L12: =I12/K12 -> 275081.48 | M12: =I12*B12 -> 1651534.5 | N12: 0.0442 | O12: =O11*(1+N12) -> 1.386749 | P12: =M12/O12 -> 1190939.7
A13: 2025-12-31 | B13: 4.9045 | C13: 0.18 | D13: 0.018 | E13: 0.015 | F13: =F12*(1+C13) -> 296810.05 | G13: =G12*(1+D13) -> 59591.76 | H13: =H12*(1+E13) -> 34340.374 | I13: =F13+G13+H13 -> 390742.19 | J13: 0.025 | K13: =K12*(1+J13) -> 1.2814477 | L13: =I13/K13 -> 304922.47 | M13: =I13*B13 -> 1916395.1 | N13: 0.045 | O13: =O12*(1+N13) -> 1.4491528 | P13: =M13/O13 -> 1322424.5
A14: 2026-05-29 (Venda) | B14: 5.155 | C14: 0.062 | D14: 0.008 | E14: -0.005 | F14: =F13*(1+C14) -> 315212.28 | G14: =G13*(1+D14) -> 60068.494 | H14: =H13*(1+E14) -> 34168.672 | I14: =F14+G14+H14 -> 409449.44 | J14: 0.015 | K14: =K13*(1+J14) -> 1.3006694 | L14: =I14/K14 -> 314799.02 | M14: =I14*B14 -> 2110711.9 | N14: 0.02 | O14: =O13*(1+N14) -> 1.4781358 | P14: =M14/O14 -> 1427955.3
A16: 2. MEMORANDO DE TRIBUTAÇÃO NA LIQUIDAÇÃO NOMINAL E REAL (MAIO 2026)
A17: Saldo Final Nominal USD | B17: =I14 -> 409449.44 | D17: Saldo Final Nominal BRL | E17: =M14 -> 2110711.9
A18: Custo Inicial USD | B18: 200000 | D18: Custo Inicial BRL | E18: =B18*B6 -> 774960
A19: Ganho de Capital Nominal BRL | B19: =E17-E18 -> 1335751.9
A20: Imposto de Renda Nominal (15%) | B20: =B19*$B$29 -> 200362.78
A22: 3. ANÁLISE EM TERMOS REAIS (DESCONTADA A INFLAÇÃO NO PERÍODO)
A23: Saldo Final Real USD (US CPI-adj) | B23: =L14 -> 314799.02 | D23: Saldo Final Real BRL (IPCA-adj) | E23: =P14 -> 1427955.3
A24: Custo Inicial Real USD | B24: =B18 -> 200000 | D24: Custo Inicial Real BRL | E24: =E18 -> 774960
A25: Ganho de Capital Real BRL | B25: =E23-E24 -> 652995.31 | D25: Ganho de Capital Real USD | E25: =B23-B24 -> 114799.02
A26: Imposto de Renda Real BRL (em t0) | B26: =B20/O14 -> 135551 | D26: Imposto de Renda Real USD (em t0) | E26: =(B20/B14)/K14 -> 29882.812
A27: Patrimônio Líquido Real BRL (pós-IR) | B27: =E23-B26 -> 1292404.3 | D27: Patrimônio Líquido Real USD (pós-IR) | E27: =B23-E26 -> 284916.2
A29: Premissa: Alíquota IR (Lei 14.754/2023) | B29: 0.15

Sheet Cenário 2 - Rebalanceamento
A1: CENÁRIO 2: ESTRATÉGIA COM REBALANCEAMENTO TÁTICO (DEZEMBRO 2021)
A2: Demonstrativo detalhado de venda de cotas de VWRA no pico cambial de 2021 para compra de ITPS e AGGU
A4: 1. EVOLUÇÃO DO PORTFÓLIO, CAMBIO E INFLAÇÃO
A5: Período | B5: PTAX Câmbio | C5: Retorno VWRA | D5: Retorno ITPS | E5: Retorno AGGU | F5: VWRA (USD) | G5: ITPS (USD) | H5: AGGU (USD) | I5: Saldo Total (USD) | J5: US CPI Anual (%) | K5: US CPI Acum. | L5: Saldo Real USD | M5: Saldo Total (BRL) | N5: IPCA Anual (%) | O5: IPCA Acum. | P5: Saldo Real BRL
A6: 2019-01-02 (Compra) | B6: 3.8748 | F6: 120000 | G6: 50000 | H6: 30000 | I6: =F6+G6+H6 -> 200000 | J6: 0 | K6: 1 | L6: =I6/K6 -> 200000 | M6: =I6*B6 -> 774960 | N6: 0 | O6: 1 | P6: =M6/O6 -> 774960
A7: 2019-12-31 | B7: 4.0307 | C7: 0.266 | D7: 0.084 | E7: 0.082 | F7: =F6*(1+C7) -> 151920 | G7: =G6*(1+D7) -> 54200 | H7: =H6*(1+E7) -> 32460 | I7: =F7+G7+H7 -> 238580 | J7: 0.0181 | K7: =K6*(1+J7) -> 1.0181 | L7: =I7/K7 -> 234338.47 | M7: =I7*B7 -> 961644.41 | N7: 0.0431 | O7: =O6*(1+N7) -> 1.0431 | P7: =M7/O7 -> 921910.08
A8: 2020-12-31 | B8: 5.1967 | C8: 0.162 | D8: 0.11 | E8: 0.056 | F8: =F7*(1+C8) -> 176531.04 | G8: =G7*(1+D8) -> 60162 | H8: =H7*(1+E8) -> 34277.76 | I8: =F8+G8+H8 -> 270970.8 | J8: 0.0136 | K8: =K7*(1+J8) -> 1.0319462 | L8: =I8/K8 -> 262582.3 | M8: =I8*B8 -> 1408154 | N8: 0.0452 | O8: =O7*(1+N8) -> 1.0902481 | P8: =M8/O8 -> 1291590.4
A9: 2021-12-31 (Antes Rebal.) | B9: 5.5805 | C9: 0.185 | D9: 0.06 | E9: -0.014 | F9: =F8*(1+C9) -> 209189.28 | G9: =G8*(1+D9) -> 63771.72 | H9: =H8*(1+E9) -> 33797.871 | I9: =F9+G9+H9 -> 306758.87 | J9: 0.047 | K9: =K8*(1+J9) -> 1.0804476 | L9: =I9/K9 -> 283918.32 | M9: =I9*B9 -> 1711867.9 | N9: 0.1006 | O9: =O8*(1+N9) -> 1.1999271 | P9: =M9/O9 -> 1426643.3
A10: 2021-12-31 (Pós Rebal.) | B10: 5.5805 | F10: =F9-B18 -> 184055.32 | G10: =G9+(B18*$G$36) -> 76689.72 | H10: =H9+(B18*$H$36) -> 46013.834 | I10: =F10+G10+H10 -> 306758.87 | J10: 0 | K10: =K9 -> 1.0804476 | L10: =I10/K10 -> 283918.32 | M10: =I10*B10 -> 1711867.9 | N10: 0 | O10: =O9 -> 1.1999271 | P10: =M10/O10 -> 1426643.3
A11: 2022-12-31 | B11: 5.2177 | C11: -0.1807 | D11: -0.127 | E11: -0.103 | F11: =F10*(1+C11) -> 150796.52 | G11: =G10*(1+D11) -> 66950.126 | H11: =H10*(1+E11) -> 41274.409 | I11: =F11+G11+H11 -> 259021.06 | J11: 0.08 | K11: =K10*(1+J11) -> 1.1668834 | L11: =I11/K11 -> 221976.81 | M11: =I11*B11 -> 1351494.2 | N11: 0.0579 | O11: =O10*(1+N11) -> 1.2694029 | P11: =M11/O11 -> 1064669.2
A12: 2023-12-31 | B12: 4.8413 | C12: 0.222 | D12: 0.039 | E12: 0.071 | F12: =F11*(1+C12) -> 184273.35 | G12: =G11*(1+D12) -> 69561.18 | H12: =H11*(1+E12) -> 44204.892 | I12: =F12+G12+H12 -> 298039.42 | J12: 0.0412 | K12: =K11*(1+J12) -> 1.214959 | L12: =I12/K12 -> 245308.21 | M12: =I12*B12 -> 1442898.3 | N12: 0.0462 | O12: =O11*(1+N12) -> 1.3280493 | P12: =M12/O12 -> 1086479.5
A13: 2024-12-31 | B13: 4.8023 | C13: 0.201 | D13: 0.012 | E13: 0.042 | F13: =F12*(1+C13) -> 221312.3 | G13: =G12*(1+D13) -> 70395.915 | H13: =H12*(1+E13) -> 46061.497 | I13: =F13+G13+H13 -> 337769.71 | J13: 0.029 | K13: =K12*(1+J13) -> 1.2501928 | L13: =I13/K13 -> 270174.08 | M13: =I13*B13 -> 1622071.5 | N13: 0.0442 | O13: =O12*(1+N13) -> 1.386749 | P13: =M13/O13 -> 1169693.6
A14: 2025-12-31 | B14: 4.9045 | C14: 0.18 | D14: 0.018 | E14: 0.015 | F14: =F13*(1+C14) -> 261148.51 | G14: =G13*(1+D14) -> 71663.041 | H14: =H13*(1+E14) -> 46752.42 | I14: =F14+G14+H14 -> 379563.97 | J14: 0.025 | K14: =K13*(1+J14) -> 1.2814477 | L14: =I14/K14 -> 296199.35 | M14: =I14*B14 -> 1861571.5 | N14: 0.045 | O14: =O13*(1+N14) -> 1.4491528 | P14: =M14/O14 -> 1284593
A15: 2026-05-29 (Venda) | B15: 5.155 | C15: 0.062 | D15: 0.008 | E15: -0.005 | F15: =F14*(1+C15) -> 277339.72 | G15: =G14*(1+D15) -> 72236.345 | H15: =H14*(1+E15) -> 46518.658 | I15: =F15+G15+H15 -> 396094.72 | J15: 0.015 | K15: =K14*(1+J15) -> 1.3006694 | L15: =I15/K15 -> 304531.44 | M15: =I15*B15 -> 2041868.3 | N15: 0.02 | O15: =O14*(1+N15) -> 1.4781358 | P15: =M15/O15 -> 1381380.7
A17: 2. EVENTO TRIBUTÁRIO DE REBALANCEAMENTO (DEZEMBRO 2021)
A18: VWRA Vendido (USD) | B18: 25133.962 | D18: Fração Vendida (%) | E18: =B18/F9 -> 0.12014938
A19: Custo Proporcional BRL | B19: =(F6*B6)*E18 -> 55866.578 | D19: Valor da Venda BRL | E19: =B18*B9 -> 140260.08
A20: Ganho de Capital BRL | B20: =E19-B19 -> 84393.499 | D20: Imposto Pago em 2021 (BRL - 15%) | E20: =B20*$B$35 -> 12659.025
A22: 3. MEMORANDO DE TRIBUTAÇÃO NA LIQUIDAÇÃO FINAL E REAL (MAIO 2026)
A23: Saldo Final Nominal USD | B23: =I15 -> 396094.72 | D23: Saldo Final Nominal BRL | E23: =M15 -> 2041868.3
A24: Custo Final BRL (Médio Ponderado) | B24: =((F6*B6)-B19) + ((G6*B6)+(G10-G9)*B10) + ((H6*B6)+(H10-H9)*B10) -> 859353.5 | D24: Custo Inicial USD | E24: 200000
A25: Ganho de Capital BRL (2026) | B25: =E23-B24 -> 1182514.8
A26: Imposto de Renda 2026 (15%) | B26: =B25*$B$35 -> 177377.22 | D26: Total de Impostos Pagos (BRL) | E26: =E20+B26 -> 190036.24
A28: 4. ANÁLISE EM TERMOS REAIS (DESCONTADA A INFLAÇÃO NO PERÍODO)
A29: Saldo Final Real USD (US CPI-adj) | B29: =L15 -> 304531.44 | D29: Saldo Final Real BRL (IPCA-adj) | E29: =P15 -> 1381380.7
A30: Custo Inicial Real USD | B30: =E24 -> 200000 | D30: Custo Inicial Real BRL | E30: =E24*B6 -> 774960
A31: Ganho de Capital Real BRL | B31: =E29-E30 -> 606420.7 | D31: Ganho de Capital Real USD | E31: =B29-B30 -> 104531.44
A32: Imposto Real BRL (em t0) | B32: =(E20/O9)+(B26/O15) -> 130550.45 | D32: Imposto Real USD (em t0) | E32: =((E20/B10)/K9)+((B26/B15)/K15) -> 28554.2
A33: Patrimônio Líquido Real BRL (pós-IR) | B33: =E29-B32 -> 1250830.2 | D33: Patrimônio Líquido Real USD (pós-IR) | E33: =B29-E32 -> 275977.24
A35: Premissa: Alíquota IR (Lei 14.754/2023) | B35: 0.15 | G35: ITPS | H35: AGGU
A36: Aloc. do produto da venda → ITPS / AGGU | G36: 0.51396592 | H36: =1-$G$36 -> 0.48603408

Sheet ETF Sources
A1: Ticker | B1: Fund | C1: ISIN | D1: Issuer | E1: Listing | F1: Trading Currency | G1: Domicile | H1: UCITS | I1: Share Class | J1: Benchmark | K1: Inception | L1: Replication | M1: Income | N1: TER / OCF | O1: Share Class AUM USD | P1: Fund AUM USD | Q1: Holdings | R1: NAV USD | S1: YTD Return | T1: Weighted Avg YTM | U1: Real Yield | V1: Effective Duration | W1: Avg Maturity | X1: Std Dev 3Y | Y1: Tracking Error 1Y | Z1: P/E | AA1: P/B | AB1: US Weight | AC1: Top-10 Weight | AD1: Data As Of | AE1: Official Source | AF1: Due Diligence Note
A2: VWRA | B2: Vanguard FTSE All-World UCITS ETF USD Accumulating | C2: IE00BK5BQT80 | D2: Vanguard | E2: London Stock Exchange | F2: USD | G2: Ireland | H2: Yes | I2: USD Accumulating | J2: FTSE All-World Index | K2: 43669 | L2: Physical, sampled | M2: Accumulating | N2: 0.0014 | O2: 53360000000 | P2: 79550000000 | Q2: 3782 | R2: 190.57 | Y2: 0.0007 | Z2: 23.2 | AA2: 3.6 | AB2: 0.617 | AC2: 0.2269921 | AD2: 2026-06-30 / NAV 2026-08-03 | AE2: https://www.vanguard.co.uk/professional/product/etf/equity/9679/ftse-all-world-ucits-etf-usd-accumulating | AF2: Large/mid-cap developed + emerging equities; check spread and NAV premium/discount live.
A3: ITPS | B3: iShares $ TIPS UCITS ETF | C3: IE00B1FZSC47 | D3: BlackRock / iShares | E3: London Stock Exchange | F3: GBP | G3: Ireland | H3: Yes | I3: USD Accumulating | J3: Bloomberg US Government Inflation-Linked Bond Index (USD) | K3: 39059 | L3: Physical, sampled | M3: Accumulating | N3: 0.001 | O3: 3534875907 | P3: 6320846497 | Q3: 48 | R3: 256.12 | S3: 0.0039 | T3: 0.0454 | U3: 0.0226 | V3: 6.55 | W3: 7.39 | X3: 0.0439 | AD3: 46244 | AE3: https://www.ishares.com/uk/individual/en/products/251714/ishares-tips-ucits-etf | AF3: ITPS is the GBP-traded LSE line; USD-traded LSE line is IDTP. Treasury issuer weight: 99.93%.
A4: AGGU | B4: iShares Core Global Aggregate Bond UCITS ETF USD Hedged Acc | C4: IE00BZ043R46 | D4: BlackRock / iShares | E4: London Stock Exchange | F4: USD | G4: Ireland | H4: Yes | I4: USD Hedged Accumulating | J4: Bloomberg Global Aggregate Bond Index | K4: 43060 | L4: Physical, sampled | M4: Accumulating | N4: 0.001 | O4: 4110903665 | P4: 14156659760 | Q4: 19980 | R4: 5.83 | S4: 0.0051 | T4: 0.0397 | V4: 6.08 | W4: 8.05 | X4: 0.0412 | AD4: 46241 | AE4: https://www.ishares.com/uk/individual/en/products/291772/ishares-core-global-aggregate-bond-ucits-etf-fund | AF4: Global investment-grade bonds hedged to USD; Treasuries 53.10%, largest issuer US Treasury 19.01%.
A6: Framework source | B6: etf-main-metrics.md — ETF Due Diligence Framework supplied by user
A7: Tax limitation | B7: Mechanisms only; confirm current rates, thresholds and filing treatment with an accountant.
A8: Execution limitation | B8: Bid-ask spread and NAV premium/discount are intraday fields; check immediately before trading.
A9: VWRA fee validation | B9: Vanguard current page: OCF 0.14%; fee reduction announced from 19 bps to 14 bps, effective 7 Oct 2025.
